{
    "sdadsasdsd": [
        {
            "id": 1,
            "type": "credit",
            "amount": 5000,
            "description": "Quick Add",
            "timestamp": "2025-05-04T14:58:51.223824"
        },
        {
            "id": 2,
            "type": "debit",
            "amount": 1.0,
            "description": "Transfer to 767587887: ",
            "timestamp": "2025-05-04T15:02:55.111838"
        },
        {
            "id": 3,
            "type": "credit",
            "amount": 10000,
            "description": "Quick Add",
            "timestamp": "2025-05-04T15:05:38.473632"
        },
        {
            "id": 4,
            "type": "credit",
            "amount": 5000,
            "description": "Quick Add",
            "timestamp": "2025-05-04T15:08:42.821661"
        },
        {
            "id": 5,
            "type": "credit",
            "amount": 10000,
            "description": "Quick Add",
            "timestamp": "2025-05-04T15:09:50.642535"
        },
        {
            "id": 6,
            "type": "credit",
            "amount": 10000,
            "description": "Quick Add",
            "timestamp": "2025-05-04T15:10:02.377569"
        },
        {
            "id": 7,
            "type": "credit",
            "amount": 10000,
            "description": "Quick Add",
            "timestamp": "2025-05-04T15:10:03.241865"
        },
        {
            "id": 8,
            "type": "credit",
            "amount": 5000,
            "description": "Quick Add",
            "timestamp": "2025-05-04T15:10:04.295288"
        },
        {
            "id": 9,
            "type": "credit",
            "amount": 1000,
            "description": "Quick Add",
            "timestamp": "2025-05-04T15:10:05.844550"
        },
        {
            "id": 10,
            "type": "debit",
            "amount": 999.0,
            "description": "Transfer to ffgd67567fghc67fg: khf876kghkudf",
            "timestamp": "2025-05-04T15:10:31.375978"
        },
        {
            "id": 11,
            "type": "debit",
            "amount": 601.0,
            "description": "Transfer to sdadsasdsd: ",
            "timestamp": "2025-05-04T15:25:05.430453"
        },
        {
            "id": 12,
            "type": "debit",
            "amount": 601.0,
            "description": "Transfer to sdadsasdsd: ",
            "timestamp": "2025-05-04T15:25:06.983942"
        },
        {
            "id": 13,
            "type": "debit",
            "amount": 601.0,
            "description": "Transfer to sdadsasdsd: ",
            "timestamp": "2025-05-04T15:25:07.790279"
        },
        {
            "id": 14,
            "type": "debit",
            "amount": 601.0,
            "description": "Transfer to sdadsasdsd: ",
            "timestamp": "2025-05-04T15:25:08.607323"
        },
        {
            "id": 15,
            "type": "debit",
            "amount": 601.0,
            "description": "Transfer to sdadsasdsd: ",
            "timestamp": "2025-05-04T15:25:09.221034"
        },
        {
            "id": 16,
            "type": "debit",
            "amount": 601.0,
            "description": "Transfer to sdadsasdsd: ",
            "timestamp": "2025-05-04T15:25:09.795819"
        },
        {
            "id": 17,
            "type": "debit",
            "amount": 601.0,
            "description": "Transfer to sdadsasdsd: ",
            "timestamp": "2025-05-04T15:25:10.311287"
        },
        {
            "id": 18,
            "type": "debit",
            "amount": 601.0,
            "description": "Transfer to sdadsasdsd: ",
            "timestamp": "2025-05-04T15:25:10.775069"
        },
        {
            "id": 19,
            "type": "debit",
            "amount": 601.0,
            "description": "Transfer to sdadsasdsd: ",
            "timestamp": "2025-05-04T15:25:11.194323"
        },
        {
            "id": 20,
            "type": "debit",
            "amount": 601.0,
            "description": "Transfer to sdadsasdsd: ",
            "timestamp": "2025-05-04T15:25:11.528981"
        },
        {
            "id": 21,
            "type": "debit",
            "amount": 601.0,
            "description": "Transfer to sdadsasdsd: ",
            "timestamp": "2025-05-04T15:25:11.933314"
        },
        {
            "id": 22,
            "type": "debit",
            "amount": 601.0,
            "description": "Transfer to sdadsasdsd: ",
            "timestamp": "2025-05-04T15:25:12.302371"
        },
        {
            "id": 23,
            "type": "debit",
            "amount": 601.0,
            "description": "Transfer to sdadsasdsd: ",
            "timestamp": "2025-05-04T15:25:12.489393"
        },
        {
            "id": 24,
            "type": "debit",
            "amount": 601.0,
            "description": "Transfer to sdadsasdsd: ",
            "timestamp": "2025-05-04T15:25:12.845154"
        },
        {
            "id": 25,
            "type": "debit",
            "amount": 601.0,
            "description": "Transfer to sdadsasdsd: ",
            "timestamp": "2025-05-04T15:25:13.218659"
        },
        {
            "id": 26,
            "type": "debit",
            "amount": 601.0,
            "description": "Transfer to sdadsasdsd: ",
            "timestamp": "2025-05-04T15:25:13.567967"
        },
        {
            "id": 27,
            "type": "debit",
            "amount": 601.0,
            "description": "Transfer to sdadsasdsd: ",
            "timestamp": "2025-05-04T15:25:13.959463"
        },
        {
            "id": 28,
            "type": "debit",
            "amount": 601.0,
            "description": "Transfer to sdadsasdsd: ",
            "timestamp": "2025-05-04T15:25:14.380201"
        },
        {
            "id": 29,
            "type": "debit",
            "amount": 601.0,
            "description": "Transfer to sdadsasdsd: ",
            "timestamp": "2025-05-04T15:25:15.052438"
        },
        {
            "id": 30,
            "type": "debit",
            "amount": 601.0,
            "description": "Transfer to sdadsasdsd: ",
            "timestamp": "2025-05-04T15:25:15.444729"
        }
    ],
    "pk": [
        {
            "id": 1,
            "type": "credit",
            "amount": 1000,
            "description": "Quick Add",
            "timestamp": "2025-05-04T15:22:58.047938"
        },
        {
            "id": 2,
            "type": "credit",
            "amount": 5000,
            "description": "Quick Add",
            "timestamp": "2025-05-04T15:22:59.912838"
        },
        {
            "id": 3,
            "type": "credit",
            "amount": 10000,
            "description": "Quick Add",
            "timestamp": "2025-05-04T15:23:13.818063"
        },
        {
            "id": 4,
            "type": "credit",
            "amount": 10000,
            "description": "Quick Add",
            "timestamp": "2025-05-04T15:23:14.197196"
        },
        {
            "id": 5,
            "type": "credit",
            "amount": 10000,
            "description": "Quick Add",
            "timestamp": "2025-05-04T15:23:15.216145"
        },
        {
            "id": 6,
            "type": "credit",
            "amount": 10000,
            "description": "Quick Add",
            "timestamp": "2025-05-04T15:23:16.117635"
        },
        {
            "id": 7,
            "type": "debit",
            "amount": 1.0,
            "description": "Transfer to NB89646250: ",
            "timestamp": "2025-05-04T15:23:54.380973"
        },
        {
            "id": 8,
            "type": "debit",
            "amount": 1.0,
            "description": "Transfer to NB89646250: ",
            "timestamp": "2025-05-04T15:23:55.747040"
        },
        {
            "id": 9,
            "type": "debit",
            "amount": 1.0,
            "description": "Transfer to NB89646250: ",
            "timestamp": "2025-05-04T15:23:56.518921"
        },
        {
            "id": 10,
            "type": "debit",
            "amount": 1.0,
            "description": "Transfer to NB89646250: ",
            "timestamp": "2025-05-04T15:23:57.337801"
        },
        {
            "id": 11,
            "type": "debit",
            "amount": 1.0,
            "description": "Transfer to NB89646250: ",
            "timestamp": "2025-05-04T15:23:57.885289"
        },
        {
            "id": 12,
            "type": "debit",
            "amount": 1.0,
            "description": "Transfer to NB89646250: ",
            "timestamp": "2025-05-04T15:23:58.374383"
        },
        {
            "id": 13,
            "type": "debit",
            "amount": 1.0,
            "description": "Transfer to NB89646250: ",
            "timestamp": "2025-05-04T15:23:58.654601"
        },
        {
            "id": 14,
            "type": "debit",
            "amount": 1.0,
            "description": "Transfer to NB89646250: ",
            "timestamp": "2025-05-04T15:23:59.703493"
        },
        {
            "id": 15,
            "type": "debit",
            "amount": 1.0,
            "description": "Transfer to NB89646250: ",
            "timestamp": "2025-05-04T15:24:00.385212"
        },
        {
            "id": 16,
            "type": "debit",
            "amount": 1.0,
            "description": "Transfer to NB89646250: ",
            "timestamp": "2025-05-04T15:24:00.675673"
        },
        {
            "id": 17,
            "type": "debit",
            "amount": 301.0,
            "description": "Transfer to NB89646250: ",
            "timestamp": "2025-05-04T15:24:05.287372"
        },
        {
            "id": 18,
            "type": "debit",
            "amount": 301.0,
            "description": "Transfer to NB89646250: ",
            "timestamp": "2025-05-04T15:24:06.153434"
        }
    ]
}